keys/__init__.py
keys/__main__.py
keys/key.py
keys/ui.py
keys/data/icons/icon.png
keys/data/ui/about.ui
keys/data/ui/error.ui
keys/data/ui/main.ui
keys/data/ui/new_rsa_keys.ui
keys/data/ui/priv_key.ui
keys_yocto-3.0.7.dist-info/LICENSE.txt
keys_yocto-3.0.7.dist-info/METADATA
keys_yocto-3.0.7.dist-info/WHEEL
keys_yocto-3.0.7.dist-info/entry_points.txt
keys_yocto-3.0.7.dist-info/top_level.txt
keys_yocto-3.0.7.dist-info/RECORD
