Metadata-Version: 2.1
Name: keys-yocto
Version: 3.0.7
Summary: Make licence keys using RSA signature verification
Author-email: Delvian Valentine <delvian.valentine@gmail.com>
Project-URL: Repository, https://github.com/delvianv/keys
Keywords: licence,license,key,rsa
Classifier: Development Status :: 5 - Production/Stable
Classifier: Intended Audience :: Developers
Classifier: License :: OSI Approved :: GNU General Public License (GPL)
Classifier: Natural Language :: English
Classifier: Operating System :: OS Independent
Classifier: Programming Language :: Python
Classifier: Topic :: Software Development
Requires-Python: >=3.8
License-File: LICENSE.txt
Requires-Dist: pyside6
Requires-Dist: rsa
